CHANGELOG.md
LICENSE
MANIFEST.in
README.rst
TODO.rst
ormconfig.py
setup.py
ormconfig.egg-info/PKG-INFO
ormconfig.egg-info/SOURCES.txt
ormconfig.egg-info/dependency_links.txt
ormconfig.egg-info/top_level.txt