Metadata-Version: 1.1
Name: ormconfig
Version: 0.1.3
Summary: A little orm for config file
Home-page: https://github.com/sunjinopensource/ormconfig/
Author: Sun Jin
Author-email: sunjinopensource@qq.com
License: UNKNOWN
Platform: UNKNOWN
Classifier: Development Status :: 3 - Alpha
Classifier: Intended Audience :: Developers
Classifier: License :: OSI Approved :: MIT License
Classifier: Operating System :: OS Independent
Classifier: Programming Language :: Python
Classifier: Programming Language :: Python :: 3
